MANIFEST.in
README.rst
setup.py
django_dbstorage/__init__.py
django_dbstorage/fields.py
django_dbstorage/models.py
django_dbstorage/storage.py
django_dbstorage/test_urls.py
django_dbstorage/tests.py
django_dbstorage/urls.py
django_dbstorage/views.py
django_dbstorage.egg-info/PKG-INFO
django_dbstorage.egg-info/SOURCES.txt
django_dbstorage.egg-info/dependency_links.txt
django_dbstorage.egg-info/requires.txt
django_dbstorage.egg-info/top_level.txt
django_dbstorage.egg-info/zip-safe