Metadata-Version: 1.0
Name: django-dbstorage
Version: 1.2
Summary: A Django file storage backend for files in the database.
Home-page: http://bitbucket.org/akoha/django-dbstorage/
Author: Akoha Inc.
Author-email: adminmail@akoha.com
License: UNKNOWN
Platform: UNKNOWN
Classifier: Development Status :: 5 - Production/Stable
Classifier: Environment :: Web Environment
Classifier: Framework :: Django
Classifier: License :: OSI Approved :: MIT License
Classifier: Operating System :: OS Independent
Classifier: Programming Language :: Python
